depthmap_toolkit/__init__.py
depthmap_toolkit/constants.py
depthmap_toolkit/depthmap.py
depthmap_toolkit/depthmap_utils.py
depthmap_toolkit/exporter.py
depthmap_toolkit/toolkit.py
depthmap_toolkit/visualisation.py
depthmap_toolkit-0.1.0.dist-info/LICENSE
depthmap_toolkit-0.1.0.dist-info/METADATA
depthmap_toolkit-0.1.0.dist-info/WHEEL
depthmap_toolkit-0.1.0.dist-info/top_level.txt
depthmap_toolkit-0.1.0.dist-info/RECORD
