Metadata-Version: 2.1
Name: depthmap-toolkit
Version: 0.1.0
Summary: Code for loading and processing depthmaps collected by CGM app
Author: Shashank Mahale
Author-email: smahale@childgrowthmonitor.org
License: GPL
Classifier: Intended Audience :: Healthcare Industry
Classifier: Programming Language :: Python
Classifier: Programming Language :: Python :: 3
Classifier: License :: OSI Approved :: GNU General Public License v3 or later (GPLv3+)
Classifier: Topic :: Scientific/Engineering
Classifier: Operating System :: OS Independent
License-File: LICENSE
